{
  "iface": "futoin.burst",
  "version": "0.1",
  "ftn3rev": "1.4",
  "funcs": {
    "noResultBurst": {
      "params": {
        "requests": {
          "type": "array",
          "desc": "List of regular FutoIn request messages"
        }
      },
      "desc": "Perform multi-call with no result for all calls"
    },
    "resultBurst": {
      "params": {
        "requests": {
          "type": "array",
          "desc": "List of regular FutoIn request messages"
        }
      },
      "result": {
        "responses": {
          "type": "array",
          "desc": "List of regular FutoIn response messages"
        }
      },
      "desc": "Perform multi-call with result at least for some calls"
    }
  },
  "requires": [
    "AllowAnonymous"
  ],
  "desc": "Burst call interface"
}